{
  "uid" : "e61f96776a8138f4",
  "name" : "Then I validate the create order service response for StatusCode 200",
  "title" : "Then I validate the create order service response for StatusCode 200",
  "time" : {
    "start" : 1562030977615,
    "stop" : 1562030977615,
    "duration" : 0
  },
  "summary" : {
    "attachments" : 1,
    "steps" : 0
  },
  "failure" : null,
  "description" : null,
  "severity" : "NORMAL",
  "status" : "PASSED",
  "suite" : {
    "uid" : "2ccce29c69b4747a",
    "name" : "Sanity Test cases for order Service - Create order | TestCase 1 | itemID,itemName | ID-01,Shoes | 200 |",
    "title" : "Sanity Test cases for order Service - Create order | TestCase 1 | itemID,itemName | ID-01,Shoes | 200 |"
  },
  "steps" : [ ],
  "attachments" : [ {
    "title" : "Response",
    "source" : "cc6316e5-b238-41c7-b581-64eebc0e8c2c-attachment.html",
    "type" : "text/html",
    "size" : 803,
    "uid" : "3049566f6cfa6a1b"
  } ],
  "issues" : [ ],
  "testIds" : [ ],
  "labels" : [ {
    "name" : "feature",
    "value" : "Testing of Order Services"
  }, {
    "name" : "language",
    "value" : "JAVA"
  }, {
    "name" : "story",
    "value" : "Sanity Test cases for order Service - Create order | TestCase 1 | itemID,itemName | ID-01,Shoes | 200 |"
  }, {
    "name" : "thread",
    "value" : "35643@Krishnendus-MBP.attlocal.net.main(1)"
  }, {
    "name" : "suite-title",
    "value" : "Sanity Test cases for order Service - Create order | TestCase 1 | itemID,itemName | ID-01,Shoes | 200 |"
  }, {
    "name" : "framework",
    "value" : "CucumberJVM"
  }, {
    "name" : "suite-name",
    "value" : "Sanity Test cases for order Service - Create order | TestCase 1 | itemID,itemName | ID-01,Shoes | 200 |"
  }, {
    "name" : "host",
    "value" : "Krishnendus-MBP.attlocal.net"
  } ],
  "parameters" : [ ]
}