{
  "uid" : "b5e0fbf26f76e06a",
  "name" : "Then I validate the create order service response for StatusCode 400",
  "title" : "Then I validate the create order service response for StatusCode 400",
  "time" : {
    "start" : 1562855633724,
    "stop" : 1562855633724,
    "duration" : 0
  },
  "summary" : {
    "attachments" : 1,
    "steps" : 0
  },
  "failure" : null,
  "description" : null,
  "severity" : "NORMAL",
  "status" : "PASSED",
  "suite" : {
    "uid" : "ed86ab82ba4e6f23",
    "name" : "Test cases for order Service - Create order | TestCase 4 | itemID,itemName,itemPrice | ID-345,Shirt, | 400 |",
    "title" : "Test cases for order Service - Create order | TestCase 4 | itemID,itemName,itemPrice | ID-345,Shirt, | 400 |"
  },
  "steps" : [ ],
  "attachments" : [ {
    "title" : "Response",
    "source" : "73cc48f8-1899-45bc-83a7-f5b5222d7903-attachment.html",
    "type" : "text/html",
    "size" : 852,
    "uid" : "10101b27a201465f"
  } ],
  "issues" : [ ],
  "testIds" : [ ],
  "labels" : [ {
    "name" : "feature",
    "value" : "Testing of Order Services"
  }, {
    "name" : "language",
    "value" : "JAVA"
  }, {
    "name" : "thread",
    "value" : "77439@Krishnendus-MBP.attlocal.net.main(1)"
  }, {
    "name" : "suite-name",
    "value" : "Test cases for order Service - Create order | TestCase 4 | itemID,itemName,itemPrice | ID-345,Shirt, | 400 |"
  }, {
    "name" : "story",
    "value" : "Test cases for order Service - Create order | TestCase 4 | itemID,itemName,itemPrice | ID-345,Shirt, | 400 |"
  }, {
    "name" : "framework",
    "value" : "CucumberJVM"
  }, {
    "name" : "host",
    "value" : "Krishnendus-MBP.attlocal.net"
  }, {
    "name" : "suite-title",
    "value" : "Test cases for order Service - Create order | TestCase 4 | itemID,itemName,itemPrice | ID-345,Shirt, | 400 |"
  } ],
  "parameters" : [ ]
}